CHANGELOG.txt
LICENCE.txt
MANIFEST.in
README.txt
setup.py
AreaPerimeterForShapes/__init__.py
AreaPerimeterForShapes.egg-info/PKG-INFO
AreaPerimeterForShapes.egg-info/SOURCES.txt
AreaPerimeterForShapes.egg-info/dependency_links.txt
AreaPerimeterForShapes.egg-info/top_level.txt