Metadata-Version: 2.1
Name: AreaPerimeterForShapes
Version: 0.0.1
Summary: Perimeter and area calculation for triangle, rectangle and circle.
Home-page: UNKNOWN
Author: Harsh Agarwal
Author-email: harshagarwal9835@gmail.com
License: MIT
Keywords: calculator
Platform: UNKNOWN
Classifier: Development Status :: 5 - Production/Stable
Classifier: Intended Audience :: Education
Classifier: Operating System :: Microsoft :: Windows :: Windows 10
Classifier: License :: OSI Approved :: MIT License
Classifier: Programming Language :: Python :: 3
